fhir_biobank/_Constants.py
fhir_biobank/__init__.py
fhir_biobank/bundle.py
fhir_biobank/condition.py
fhir_biobank/custodian.py
fhir_biobank/diagnosis.py
fhir_biobank/helperFunctions.py
fhir_biobank/patient.py
fhir_biobank/specimen.py
fhir_biobank/storageTemperature.py
fhir_biobank-0.1.3.dist-info/LICENSE
fhir_biobank-0.1.3.dist-info/METADATA
fhir_biobank-0.1.3.dist-info/WHEEL
fhir_biobank-0.1.3.dist-info/top_level.txt
fhir_biobank-0.1.3.dist-info/RECORD
