Metadata-Version: 2.1
Name: fhir-biobank
Version: 0.1.3
Summary: Python library working with FHIR standard in scope of biobanks MIABIS requirements
Home-page: https://fhir-biobank.readthedocs.io/
Author: Simon Konar
Author-email: simon.konar@gmail.com
License: MIT
Platform: UNKNOWN
Classifier: Intended Audience :: Developers
Classifier: License :: OSI Approved :: MIT License
Classifier: Programming Language :: Python
Classifier: Programming Language :: Python :: 3.7
Classifier: Operating System :: OS Independent
Requires-Dist: fhirclient
Requires-Dist: pytest
